{
  "project_info": {
    "project_number": "471748242246",
    "project_id": "aubsystemm",
    "storage_bucket": "aubsystemm.appspot.com"
  },
  "client": [
    {
      "client_info": {
        "mobilesdk_app_id": "1:471748242246:android:f88313aeaa1a06d4b4d347",
        "android_client_info": {
          "package_name": "com.example.aub_gymsystem"
        }
      },
      "oauth_client": [],
      "api_key": [
        {
          "current_key": "AIzaSyDB9KYchkQISv6P-q_n7NlDaylh6-xmvwA"
        }
      ],
      "services": {
        "appinvite_service": {
          "other_platform_oauth_client": []
        }
      }
    }
  ],
  "configuration_version": "1"
}